ScrollableFrame/__init__.py
ScrollableFrame-0.0.4.dist-info/LICENSE
ScrollableFrame-0.0.4.dist-info/METADATA
ScrollableFrame-0.0.4.dist-info/WHEEL
ScrollableFrame-0.0.4.dist-info/top_level.txt
ScrollableFrame-0.0.4.dist-info/RECORD
