Metadata-Version: 2.1
Name: ScrollableFrame
Version: 0.0.4
Summary: Your tkinter ScrollableFrame
Home-page: https://github.com/larryw3i/ScrollableFrame
Author: larryw3i
Author-email: 
License: UNKNOWN
Platform: UNKNOWN
Classifier: Programming Language :: Python :: 3
Classifier: License :: OSI Approved :: MIT License
Classifier: Operating System :: OS Independent
Requires-Python: >=3.6
License-File: LICENSE
